pysyncrosim/__init__.py
pysyncrosim/_version.py
pysyncrosim/environment.py
pysyncrosim/folder.py
pysyncrosim/helper.py
pysyncrosim/library.py
pysyncrosim/project.py
pysyncrosim/raster.py
pysyncrosim/scenario.py
pysyncrosim/session.py
tests/__init__.py
tests/test_pysyncrosim.py
pysyncrosim-2.1.3.dist-info/LICENSE
pysyncrosim-2.1.3.dist-info/METADATA
pysyncrosim-2.1.3.dist-info/WHEEL
pysyncrosim-2.1.3.dist-info/top_level.txt
pysyncrosim-2.1.3.dist-info/RECORD
