Metadata-Version: 2.2
Name: pysyncrosim
Version: 2.1.3
Summary: Python interface to SyncroSim
Home-page: https://syncrosim.com/
Author: ApexRMS
Author-email: info@apexrms.com
License-File: LICENSE
Dynamic: author
Dynamic: author-email
Dynamic: description
Dynamic: description-content-type
Dynamic: home-page
Dynamic: summary
